codesjac/__init__.py
codesjac/tstclass.py
codesjac-0.1.0.dist-info/METADATA
codesjac-0.1.0.dist-info/WHEEL
codesjac-0.1.0.dist-info/RECORD
